geecs_data_utils/__init__.py
geecs_data_utils/geecs_paths_config.py
geecs_data_utils/plotting_utils.py
geecs_data_utils/scan_data.py
geecs_data_utils/scan_paths.py
geecs_data_utils/scans_database/builder.py
geecs_data_utils/scans_database/database.py
geecs_data_utils/scans_database/entries.py
geecs_data_utils/scans_database/filter_models.py
geecs_data_utils/scans_database/filters/undulator.yml
geecs_data_utils/type_defs.py
geecs_data_utils/utils.py
geecs_data_utils-0.1.1.dist-info/LICENSE.txt
geecs_data_utils-0.1.1.dist-info/METADATA
geecs_data_utils-0.1.1.dist-info/WHEEL
geecs_data_utils-0.1.1.dist-info/RECORD
