Metadata-Version: 2.3
Name: geecs-data-utils
Version: 0.1.1
Summary: Utilities for working with data generated by GEECS.
License: BSD-3-Clause
Keywords: GEECS,LPA
Author: Sam Barber
Author-email: sbarber@lbl.gov
Requires-Python: >=3.9,<3.13
Classifier: License :: OSI Approved :: BSD License
Classifier: Operating System :: OS Independent
Classifier: Programming Language :: Python :: 3
Classifier: Programming Language :: Python :: 3.9
Classifier: Programming Language :: Python :: 3.10
Classifier: Programming Language :: Python :: 3.11
Classifier: Programming Language :: Python :: 3.12
Classifier: Programming Language :: Python :: 3 :: Only
Requires-Dist: duckdb (>=1.1.3,<2.0.0)
Requires-Dist: nptdms (>=1.7.0,<2.0.0)
Requires-Dist: numpy (<2.0)
Requires-Dist: pandas (>=2.0,<3.0)
Requires-Dist: pyarrow (>=14.0.0,<15.0.0)
Requires-Dist: pydantic (>=2.0,<3.0)
Requires-Dist: pyyaml (>=6.0.1,<7.0.0)
Project-URL: Changelog, https://github.com/GEECS-BELLA/GEECS-Plugins/releases
Project-URL: Homepage, https://github.com/GEECS-BELLA/GEECS-Plugins
Project-URL: Issues, https://github.com/GEECS-BELLA/GEECS-Plugins/issues
Project-URL: Repository, https://github.com/GEECS-BELLA/GEECS-Plugins
Project-URL: Source (subdir), https://github.com/GEECS-BELLA/GEECS-Plugins/tree/master/GEECS-Data-Utils
